Metadata-Version: 2.1
Name: jivago-streams
Version: 0.5.5
Summary: Chainable functional-style operations for Python3.
Home-page: https://github.com/jivago-python/jivago-streams
Author: Kento A. Lauzon
Author-email: kento.lauzon@ligature.ca
License: UNKNOWN
Platform: UNKNOWN
Classifier: Development Status :: 4 - Beta
Classifier: Intended Audience :: Developers
Classifier: Topic :: Software Development :: Libraries
Classifier: License :: OSI Approved :: MIT License
Classifier: Programming Language :: Python :: 3.5
Classifier: Programming Language :: Python :: 3.6
Classifier: Programming Language :: Python :: 3.7
